{
    "name": "quote-block",
    "title": "Quote Block",
    "description": "Renders people and plants content field",
    "style": "file:./style.css",
    "script": "",
    "category": "design",
    "icon": "format-quote",
    "apiVersion": 2,
    "keywords": [],
    "acf": {
        "mode": "preview",
	"renderTemplate": "render.php"
    },
    "styles": [],
    "supports": {
        "align": false,
        "anchor": false,
        "alignContent": false,
        "color": {
            "text": false,
            "background": true,
            "link": false
        },
        "alignText": false,
        "fullHeight": false
    },
    "attributes": {
        "backgroundColor": {
            "type": "string",
            "default": "tertiary"
        }
    }
}